[
  {
    "norma_id": "DA-284-2024",
    "tipo_norma": "DA",
    "numero": "284",
    "anio": 2024,
    "fecha_boletin": "2024-05-09",
    "numero_boletin": "35417",
    "pagina_boletin": "8",
    "organismo": "JEFATURA DE GABINETE DE MINISTROS",
    "titulo": "MODIFICACION",
    "sumario": "PRESUPUESTO ADMINISTRACION NACIONAL",
    "texto_resumido": "MODIFICASE EL PRESUPUESTO GENERAL DE LA ADMINISTRACION NACIONAL PARA EL EJERCICIO 2024, DE ACUERDO CON EL DETALLE OBRANTE EN LAS PLANILLAS ANEXAS (IF-2024-43632836-APN-SSP#MEC) AL PRESENTE ARTICULO, QUE FORMAN PARTE INTEGRANTE DE LA PRESENTE MEDIDA.",
    "tipo_accion": "MODIFICACION",
    "url_infoleg": "http://servicios.infoleg.gob.ar/infolegInternet/anexos/395000-399999/399031/norma.htm",
    "url_bora": "https://www.boletinoficial.gob.ar/detalleAviso/primera/0/35417/20240509",
    "pdf_hash": "98ee7e54d87a5dc9213ef2c5ea97e762c70be501d40fb7a522b4ac1484aab990"
  },
  {
    "norma_id": "DA-470-2024",
    "tipo_norma": "DA",
    "numero": "470",
    "anio": 2024,
    "fecha_boletin": "2024-06-06",
    "numero_boletin": "35437",
    "pagina_boletin": "19",
    "organismo": "JEFATURA DE GABINETE DE MINISTROS",
    "titulo": "MODIFICACION",
    "sumario": "PRESUPUESTO ADMINISTRACION NACIONAL",
    "texto_resumido": "MODIFICASE EL PRESUPUESTO GENERAL DE LA ADMINISTRACION NACIONAL PARA EL EJERCICIO 2024.",
    "tipo_accion": "MODIFICACION",
    "url_infoleg": "http://servicios.infoleg.gob.ar/infolegInternet/anexos/400000-404999/400246/norma.htm",
    "url_bora": "https://www.boletinoficial.gob.ar/detalleAviso/primera/0/35437/20240606",
    "pdf_hash": "76b67df31d58a9c6fafd57bda1569a8b12a24475936f5b1d41ecc21d5e43cebf"
  },
  {
    "norma_id": "DA-858-2024",
    "tipo_norma": "DA",
    "numero": "858",
    "anio": 2024,
    "fecha_boletin": "2024-09-02",
    "numero_boletin": "35495",
    "pagina_boletin": "24",
    "organismo": "JEFATURA DE GABINETE DE MINISTROS",
    "titulo": "MODIFICACION.",
    "sumario": "PRESUPUESTO GENERAL DE LA ADMINISTRACION NACIONAL PARA EL EJERCICIO 2024",
    "texto_resumido": "MODIFICASE EL PRESUPUESTO GENERAL DE LA ADMINISTRACION NACIONAL PARA EL EJERCICIO 2024, DE ACUERDO CON EL DETALLE OBRANTE EN LAS PLANILLAS ANEXAS (IF-2024-85364156-APN-SSP#MEC) AL PRESENTE ARTICULO, QUE FORMAN PARTE INTEGRANTE DE LA PRESENTE MEDIDA.",
    "tipo_accion": "MODIFICACION",
    "url_infoleg": "http://servicios.infoleg.gob.ar/infolegInternet/anexos/400000-404999/403576/norma.htm",
    "url_bora": "https://www.boletinoficial.gob.ar/detalleAviso/primera/0/35495/20240902",
    "pdf_hash": "715a86a6dc66f3d107e5fbdf29593d58b8e3ac27f6d3a3cb5abb729de64471b3"
  },
  {
    "norma_id": "DA-861-2024",
    "tipo_norma": "DA",
    "numero": "861",
    "anio": 2024,
    "fecha_boletin": "2024-09-02",
    "numero_boletin": "35495",
    "pagina_boletin": "25",
    "organismo": "JEFATURA DE GABINETE DE MINISTROS",
    "titulo": "MODIFICACION",
    "sumario": "PRESUPUESTO GENERAL DE LA ADMINISTRACION NACIONAL PARA EL EJERCICIO 2024",
    "texto_resumido": "MODIFICASE EL PRESUPUESTO GENERAL DE LA ADMINISTRACION NACIONAL PARA EL EJERCICIO 2024, DE ACUERDO CON EL DETALLE OBRANTE EN LAS PLANILLAS ANEXAS (IF-2024-90749380-APN-SSP#MEC) AL PRESENTE ARTICULO, QUE FORMAN PARTE INTEGRANTE DE LA PRESENTE MEDIDA.",
    "tipo_accion": "MODIFICACION",
    "url_infoleg": "http://servicios.infoleg.gob.ar/infolegInternet/anexos/400000-404999/403577/norma.htm",
    "url_bora": "https://www.boletinoficial.gob.ar/detalleAviso/primera/0/35495/20240902",
    "pdf_hash": "286bf4396f1bc1ebd3ba434fe42fd03c975f2884e36e1ec328d707c12834649d"
  },
  {
    "norma_id": "DA-910-2024",
    "tipo_norma": "DA",
    "numero": "910",
    "anio": 2024,
    "fecha_boletin": "2024-09-30",
    "numero_boletin": "35515",
    "pagina_boletin": "18",
    "organismo": "JEFATURA DE GABINETE DE MINISTROS",
    "titulo": "MODIFICACION",
    "sumario": "PRESUPUESTO ADMINISTRACION NACIONAL",
    "texto_resumido": "MODIFICASE EL PRESUPUESTO GENERAL DE LA ADMINISTRACION NACIONAL PARA EL EJERCICIO 2024, DE ACUERDO CON EL DETALLE OBRANTE EN LAS PLANILLAS ANEXAS (IF-2024-101895185-APN-SSP#MEC) AL PRESENTE ARTICULO, QUE FORMAN PARTE INTEGRANTE DE LA PRESENTE MEDIDA.",
    "tipo_accion": "MODIFICACION",
    "url_infoleg": "http://servicios.infoleg.gob.ar/infolegInternet/anexos/400000-404999/404636/norma.htm",
    "url_bora": "https://www.boletinoficial.gob.ar/detalleAviso/primera/0/35515/20240930",
    "pdf_hash": "a4f6242f48c93b4786b3875d19116d70486ff12a60070ff3f97742f53096d2ee"
  },
  {
    "norma_id": "DA-1015-2024",
    "tipo_norma": "DA",
    "numero": "1015",
    "anio": 2024,
    "fecha_boletin": "2024-10-31",
    "numero_boletin": "35537",
    "pagina_boletin": "11",
    "organismo": "JEFATURA DE GABINETE DE MINISTROS",
    "titulo": "MODIFICACIONES",
    "sumario": "PRESUPUESTO ADMINISTRACION NACIONAL",
    "texto_resumido": "MODIFICASE EL PRESUPUESTO GENERAL DE LA ADMINISTRACION NACIONAL PARA EL EJERCICIO 2024, DE ACUERDO CON EL DETALLE OBRANTE EN LAS PLANILLAS ANEXAS (IF-2024-114299514-APN-SSP#MEC) AL PRESENTE ARTICULO, QUE FORMAN PARTE INTEGRANTE DE LA PRESENTE MEDIDA. MODIFICASE EL PRESUPUESTO GENERAL DE LA ADMINISTRACION NACIONAL PARA EL EJERCICIO 2024 EN LO QUE CORRESPONDE A LOS CARGOS, DE ACUERDO CON EL DETALLE OBRANTE EN LAS PLANILLAS ANEXAS (IF-2024-114299769- APN-SSP#MEC) AL PRESENTE ARTICULO.",
    "tipo_accion": "MODIFICACION",
    "url_infoleg": "http://servicios.infoleg.gob.ar/infolegInternet/anexos/405000-409999/405849/norma.htm",
    "url_bora": "https://www.boletinoficial.gob.ar/detalleAviso/primera/0/35537/20241031",
    "pdf_hash": "bb920a442a8e31c11765e9ca67b5bf9d6658ed18731dd124145e15e9250a0dc2"
  },
  {
    "norma_id": "DA-1018-2024",
    "tipo_norma": "DA",
    "numero": "1018",
    "anio": 2024,
    "fecha_boletin": "2024-11-29",
    "numero_boletin": "35557",
    "pagina_boletin": "18",
    "organismo": "JEFATURA DE GABINETE DE MINISTROS",
    "titulo": "MODIFICACION",
    "sumario": "PRESUPUESTO ADMINISTRACION NACIONAL",
    "texto_resumido": "MODIFICASE EL PRESUPUESTO GENERAL DE LA ADMINISTRACION NACIONAL PARA EL EJERCICIO 2024, DE ACUERDO CON EL DETALLE OBRANTE EN LAS PLANILLAS ANEXAS (IF-2024-125944582-APN-SSP#MEC) AL PRESENTE ARTICULO, QUE FORMAN PARTE INTEGRANTE DE LA PRESENTE MEDIDA.",
    "tipo_accion": "MODIFICACION",
    "url_infoleg": "http://servicios.infoleg.gob.ar/infolegInternet/anexos/405000-409999/406660/norma.htm",
    "url_bora": "https://www.boletinoficial.gob.ar/detalleAviso/primera/0/35557/20241129",
    "pdf_hash": "9d7914cc52200f7e584a74daab04dbe42b3b843b8b472ccc1d42c086d712e044"
  },
  {
    "norma_id": "DA-1022-2024",
    "tipo_norma": "DA",
    "numero": "1022",
    "anio": 2024,
    "fecha_boletin": "2024-12-31",
    "numero_boletin": "35578",
    "pagina_boletin": "25",
    "organismo": "JEFATURA DE GABINETE DE MINISTROS",
    "titulo": "MODIFICACION",
    "sumario": "PRESUPUESTO ADMINISTRACION NACIONAL",
    "texto_resumido": "MODIFICASE EL PRESUPUESTO GENERAL DE LA ADMINISTRACION NACIONAL PARA EL EJERCICIO 2024, DE ACUERDO CON EL DETALLE OBRANTE EN LAS PLANILLAS ANEXAS (IF-2024-140012809-APN-SSP#MEC) AL PRESENTE ARTICULO, QUE FORMAN PARTE INTEGRANTE DE LA PRESENTE MEDIDA. MODIFICANSE LAS CUOTAS DE COMPROMISO PRESUPUESTARIO PARA EL CUARTO TRIMESTRE DEL AÑO 2024 Y LAS CUOTAS DE DEVENGADO PRESUPUESTARIO PARA EL MES DE DICIEMBRE DE 2024, DE ACUERDO CON EL DETALLE OBRANTE EN LAS PLANILLAS ANEXAS (IF-2024-140012598-APN-SSP#MEC) AL PRESENTE ARTICULO, QUE FORMAN PARTE INTEGRANTE DE ESTA MEDIDA.",
    "tipo_accion": "MODIFICACION",
    "url_infoleg": "http://servicios.infoleg.gob.ar/infolegInternet/anexos/405000-409999/407924/norma.htm",
    "url_bora": "https://www.boletinoficial.gob.ar/detalleAviso/primera/0/35578/20241231",
    "pdf_hash": "a73bde0fee527404a3c8a2b46a0cc6265c70931ff17258f831b2c78e12f1f425"
  }
]